pytail/__init__.py
pytail/pytail.py
pytail_r3ap3rpy-0.1.5.data/scripts/pytail
pytail_r3ap3rpy-0.1.5.dist-info/METADATA
pytail_r3ap3rpy-0.1.5.dist-info/WHEEL
pytail_r3ap3rpy-0.1.5.dist-info/top_level.txt
pytail_r3ap3rpy-0.1.5.dist-info/RECORD
