Metadata-Version: 2.1
Name: pytail-r3ap3rpy
Version: 0.1.5
Home-page: https://pypi.org/project/pytail-r3ap3rpy/
Author: Szabó Dániel Ernő
Author-email: r3ap3rpy@gmail.com
License: MIT
Classifier: Programming Language :: Python :: 3.10
Classifier: License :: OSI Approved :: MIT License
Classifier: Operating System :: OS Independent
Requires-Python: >=3.10.0
